{
    "info": {
        "url_png_icon_64x64": "https://github.com/fisch192/southtyrolpool.github.io/blob/main/iphone-60x60@3x.png?raw=true",
        "url_png_logo": "https://github.com/fisch192/southtyrolpool.github.io/blob/main/southtyrolpool-name.jpg?raw=true",
        "location": "Canberra, Australia",
        "social": {
            "twitter_handle": "Southtyrolpool",
            "telegram_handle": "Southtyrolpool",
            "facebook_handle": "",
            "youtube_handle": "",
            "twitch_handle": "",
            "discord_handle": "",
            "github_handle": ""
        },
        "company": {
            "name": "Juan Carlos",
            "addr": "",
            "city": "Canberra",
            "country": "AU",
            "company_id": "",
            "vat_id": ""
        },
        "about": {
            "me": "Testing a new pool",
            "server": "Raspberry Pi 4 powered with green energy",
            "company": ""
        },
    "my-pool-ids": {
        "0": "3d5ca73563df2e956b4255e09e9406f0e908c5321e9e33303d8eaa7b",
        "1": ""
      }
    }
}
